framl/__init__.py
framl/assembler.py
framl/skeleton/.dockerignore
framl/skeleton/.gitignore
framl/skeleton/Dockerfile
framl/skeleton/main.py
framl/skeleton/requirements.txt
framl/skeleton/validator.py
framl/skeleton/model/model.py
framl-0.4.data/scripts/framl
framl-0.4.dist-info/METADATA
framl-0.4.dist-info/WHEEL
framl-0.4.dist-info/top_level.txt
framl-0.4.dist-info/RECORD
