Metadata-Version: 2.1
Name: framl
Version: 0.4
Summary: Frame to create ML predictor and trainer
Home-page: UNKNOWN
Author: Machavia Pichet
Author-email: machavia.pichet@blablacar.com
License: MIT
Platform: UNKNOWN
